Discrete_Dynamical_Reservoir/DDS_Reservoir.py
Discrete_Dynamical_Reservoir/__init__.py
Discrete_Dynamical_Reservoir-0.1.5.dist-info/LICENSE
Discrete_Dynamical_Reservoir-0.1.5.dist-info/METADATA
Discrete_Dynamical_Reservoir-0.1.5.dist-info/WHEEL
Discrete_Dynamical_Reservoir-0.1.5.dist-info/top_level.txt
Discrete_Dynamical_Reservoir-0.1.5.dist-info/RECORD
